pyconversions/__init__.py
pyconversions/pyconv.py
pyconversions-0.0.12.dist-info/METADATA
pyconversions-0.0.12.dist-info/WHEEL
pyconversions-0.0.12.dist-info/top_level.txt
pyconversions-0.0.12.dist-info/RECORD
