Metadata-Version: 2.1
Name: pyconversions
Version: 0.0.12
Summary: Convert Unit Length Datas
Home-page: UNKNOWN
Author: Logan
Author-email: <lgnx@gnamil.com>
License: UNKNOWN
Keywords: python,unitlength,length,distances,diameters,meters
Platform: UNKNOWN
Classifier: Development Status :: 1 - Planning
Classifier: Intended Audience :: Developers
Classifier: Programming Language :: Python :: 3
Classifier: Operating System :: Unix
Classifier: Operating System :: MacOS :: MacOS X
Classifier: Operating System :: Microsoft :: Windows
